ez_query/__init__.py
ez_query/chatgpt_communicator.py
ez_query/config.py
ez_query/main.py
ez_query/processor.py
ez_query/schema_req.py
ez_query-0.0.3.dist-info/METADATA
ez_query-0.0.3.dist-info/WHEEL
ez_query-0.0.3.dist-info/entry_points.txt
ez_query-0.0.3.dist-info/licenses/LICENSE.md
ez_query-0.0.3.dist-info/RECORD
