Metadata-Version: 2.1
Name: ez_query
Version: 0.0.3
Summary: SQL Query Generator (using your table schemas) powered by ChatGPT.
Project-URL: Source Code, https://github.com/AbhishekVel/ez-query
Author-email: Abhishek Velayudhamm <velayudham.abhishek@gmail.com>
License-File: LICENSE.md
Classifier: License :: OSI Approved :: MIT License
Classifier: Operating System :: OS Independent
Classifier: Programming Language :: Python :: 3
Requires-Python: >=3.8
Requires-Dist: argparse==1.4.0
Requires-Dist: mysql-connector-python==8.0.32
Requires-Dist: openai==0.27.0
Requires-Dist: prompt-toolkit==3.0.38
Requires-Dist: python-dotenv==0.21.1
